django_mobileesp/__init__.py
django_mobileesp/detector.py
django_mobileesp/mdetect.py
django_mobileesp/middleware.py
django_mobileesp/utils.py
Django_Mobileesp-1.0.1.dist-info/DESCRIPTION.rst
Django_Mobileesp-1.0.1.dist-info/METADATA
Django_Mobileesp-1.0.1.dist-info/metadata.json
Django_Mobileesp-1.0.1.dist-info/RECORD
Django_Mobileesp-1.0.1.dist-info/top_level.txt
Django_Mobileesp-1.0.1.dist-info/WHEEL
