Metadata-Version: 2.0
Name: Django-Mobileesp
Version: 1.0.1
Summary: Detect request's mobile user agents using the mobileesp lib.
Home-page: https://github.com/laginha/django-mobileesp
Author: Diogo Laginha
Author-email: diogo.laginha.machado@gmail.com
License: MIT
Platform: UNKNOWN
Classifier: License :: OSI Approved :: MIT License
Classifier: Programming Language :: Python :: 2
Classifier: Intended Audience :: Developers
Requires-Dist: django
